dinamopy/__init__.py
dinamopy/dinamo.py
dinamopy/dinamo_hooks.py
dinamopy-0.1.0.dist-info/LICENSE
dinamopy-0.1.0.dist-info/METADATA
dinamopy-0.1.0.dist-info/WHEEL
dinamopy-0.1.0.dist-info/top_level.txt
dinamopy-0.1.0.dist-info/RECORD
