Metadata-Version: 2.1
Name: dinamopy
Version: 0.1.0
Summary: DynamoDB wrapper
Home-page: https://github.com/rasimandiran/dinamopy
Author: Rasim Andiran
Author-email: rasimandiran@gmail.com
License: UNKNOWN
Platform: UNKNOWN
Classifier: Programming Language :: Python :: 3
Classifier: License :: OSI Approved :: MIT License
Classifier: Operating System :: OS Independent
Requires-Python: >=3.6
